{
    "EN_PR": {
        "league_name": "Premier League",
        "label": [
            "2019/2020",
            "2018/2019",
            "2017/2018",
            "2016/2017",
            "2015/2016",
            "2014/2015",
            "2013/2014",
            "2012/2013",
            "2011/2012",
            "2010/2011",
            "2009/2010",
            "2008/2009",
            "2007/2008",
            "2006/2007",
            "2005/2006",
            "2004/2005",
            "2003/2004",
            "2002/2003",
            "2001/2002",
            "2000/2001"
        ]
    },
    "EU_CL": {
        "league_name": "UEFA Champions League",
        "label": [
            "2019/2020",
            "2018/2019",
            "2017/2018",
            "2016/2017",
            "2015/2016",
            "2014/2015",
            "2013/2014",
            "2012/2013",
            "2011/2012",
            "2010/2011",
            "2009/2010",
            "2008/2009",
            "2006/2007",
            "2004/2005"
        ]
    },
    "EU_UC": {
        "league_name": "UEFA Europa League",
        "label": [
            "2019/2020",
            "2018/2019",
            "2017/2018",
            "2016/2017",
            "2015/2016",
            "2014/2015",
            "2013/2014",
            "2012/2013",
            "2011/2012",
            "2010/2011",
            "2008/2009",
            "2006/2007",
            "2009/2010"
        ]
    },
    "EN_FA": {
        "league_name": "FA Cup",
        "label": [
            "2019/2020",
            "2018/2019",
            "2017/2018",
            "2016/2017",
            "2015/2016",
            "2014/2015",
            "2013/2014",
            "2012/2013",
            "2011/2012",
            "2010/2011",
            "2009/2010",
            "2008/2009",
            "2007/2008",
            "2006/2007",
            "2005/2006",
            "2004/2005"
        ]
    },
    "EN_LC": {
        "league_name": "EFL Cup",
        "label": [
            "2019/2020",
            "2018/2019",
            "2017/2018",
            "2016/2017",
            "2015/2016",
            "2014/2015",
            "2013/2014",
            "2012/2013",
            "2011/2012",
            "2010/2011",
            "2009/2010",
            "2008/2009"
        ]
    },
    "EN_PD": {
        "league_name": "Professional Development League",
        "label": [
            "2019/2020",
            "2018/2019",
            "2017/2018",
            "2016/2017",
            "2015/2016",
            "2014/2015"
        ]
    },
    "AFAPL12": {
        "league_name": "U18 Professional Development League",
        "label": [
            "2019/2020",
            "2018/2019",
            "2017/2018",
            "2016/2017",
            "2015/2016",
            "2014/2015"
        ]
    },
    "AFAPL": {
        "league_name": "U18 Premier League",
        "label": [
            "2019/2020",
            "2018/2019",
            "2017/2018",
            "2016/2017",
            "2015/2016",
            "2014/2015",
            "2013/2014",
            "2012/2013",
            "2011/2012"
        ]
    },
    "EN_PC": {
        "league_name": "Premier League Cup",
        "label": [
            "2019/2020",
            "2018/2019",
            "2017/2018",
            "2016/2017",
            "2015/2016",
            "2014/2015"
        ]
    },
    "EN_PLIC": {
        "league_name": "Premier League International Cup",
        "label": [
            "2019/2020",
            "2018/2019",
            "2017/2018",
            "2016/2017",
            "2015/2016",
            "2014/2015"
        ]
    },
    "EN_D1": {
        "league_name": "English Football League - Championship",
        "label": [
            "2019/2020",
            "2018/2019",
            "2017/2018",
            "2016/2017",
            "2014/2015",
            "2013/2014",
            "2012/2013",
            "2011/2012",
            "2010/2011",
            "2009/2010"
        ]
    },
    "EN_FL": {
        "league_name": "EFL Trophy",
        "label": [
            "2019/2020",
            "2018/2019",
            "2017/2018",
            "2016/2017"
        ]
    },
    "IG_AT": {
        "league_name": "Premier League Asia Trophy",
        "label": [
            "2019/2020",
            "2017/2018"
        ]
    },
    "PL_D1": {
        "league_name": "Premier League 2 - Division 1",
        "label": [
            "2019/2020",
            "2018/2019",
            "2017/2018",
            "2016/2017"
        ]
    },
    "PL_D2": {
        "league_name": "Premier League 2 - Division 2",
        "label": [
            "2019/2020",
            "2018/2019",
            "2017/2018",
            "2016/2017"
        ]
    },
    "PLC_U18": {
        "league_name": "U18 Premier League Cup",
        "label": [
            "2019/2020",
            "2018/2019",
            "2017/2018"
        ]
    },
    "PLC_U16": {
        "league_name": "English U16 Premier League Cup",
        "label": [
            "2019/2020",
            "2018/2019",
            "2017/2018"
        ]
    },
    "EN_D2": {
        "league_name": "English Football League - League One",
        "label": [
            "2019/2020",
            "2018/2019",
            "2017/2018",
            "2016/2017",
            "2013/2014",
            "2008/2009"
        ]
    },
    "ES_PL": {
        "league_name": "La Liga",
        "label": [
            "2019/2020",
            "2018/2019",
            "2017/2018",
            "2016/2017",
            "2015/2016",
            "2014/2015",
            "2013/2014",
            "2012/2013",
            "2011/2012",
            "2010/2011",
            "2006/2007",
            "2003/2004",
            "2007/2008"
        ]
    },
    "ES_SD": {
        "league_name": "Spanish Segunda Division",
        "label": [
            "2017/2018",
            "2016/2017",
            "2015/2016",
            "2014/2015",
            "2013/2014",
            "2012/2013",
            "2011/2012",
            "2010/2011"
        ]
    },
    "ES_SC": {
        "league_name": "Supercopa",
        "label": [
            "2019/2020",
            "2018/2019",
            "2017/2018",
            "2016/2017",
            "2015/2016",
            "2014/2015",
            "2013/2014",
            "2012/2013",
            "2011/2012",
            "2010/2011"
        ]
    },
    "EU_SC": {
        "league_name": "UEFA Super Cup",
        "label": [
            "2019/2020",
            "2018/2019",
            "2017/2018",
            "2016/2017",
            "2015/2016",
            "2014/2015",
            "2013/2014",
            "2012/2013",
            "2011/2012",
            "2010/2011"
        ]
    },
    "ES_CR": {
        "league_name": "Copa Del Rey",
        "label": [
            "2019/2020",
            "2018/2019",
            "2017/2018",
            "2016/2017",
            "2015/2016",
            "2014/2015",
            "2013/2014",
            "2012/2013",
            "2011/2012",
            "2010/2011"
        ]
    },
    "IG_CL": {
        "league_name": "FIFA Club World Cup",
        "label": [
            "2019/2020",
            "2018/2019",
            "2017/2018",
            "2016/2017",
            "2015/2016",
            "2014/2015",
            "2013/2014",
            "2012/2013",
            "2011/2012",
            "2010/2011"
        ]
    },
    "IG_CT": {
        "league_name": "International Champions Cup",
        "label": [
            "2019/2020",
            "2018/2019",
            "2017/2018",
            "2016/2017",
            "2015/2016",
            "2014/2015",
            "2013/2014"
        ]
    },
    "AU_DI": {
        "league_name": "Audi Cup",
        "label": [
            "2015/2016",
            "2013/2014"
        ]
    },
    "ES_JG": {
        "league_name": "Trofeo Joan Gamper",
        "label": [
            "2019/2020",
            "2018/2019",
            "2017/2018",
            "2016/2017"
        ]
    },
    "ES_CT": {
        "league_name": "Supercopa de Catalunya",
        "label": [
            "2018/2019",
            "2017/2018",
            "2016/2017"
        ]
    },
    "EU_YL": {
        "league_name": "UEFA Youth League",
        "label": [
            "2019/2020",
            "2018/2019",
            "2017/2018",
            "2016/2017",
            "2015/2016",
            "2014/2015",
            "2013/2014"
        ]
    },
    "EN_YP": {
        "league_name": "English FA Youth Cup",
        "label": [
            "2019/2020",
            "2018/2019",
            "2017/2018",
            "2016/2017",
            "2015/2016"
        ]
    },
    "WO_SL": {
        "league_name": "English Women's Super League",
        "label": [
            "2019/2020",
            "2018/2019",
            "2017/2018",
            "2016/2017",
            "2015/2016",
            "2014/2015",
            "2013/2014"
        ]
    },
    "WO_SS": {
        "league_name": "Women's Super League Spring Series",
        "label": [
            "2016/2017"
        ]
    },
    "LD_S3": {
        "league_name": "Scottish League Two",
        "label": [
            "2019/2020",
            "2018/2019"
        ]
    },
    "EN_D3": {
        "league_name": "English Football League - League Two",
        "label": [
            "2019/2020",
            "2018/2019",
            "2017/2018"
        ]
    },
    "LD_S1": {
        "league_name": "Scottish Championship",
        "label": [
            "2019/2020",
            "2018/2019"
        ]
    },
    "WO_SL2": {
        "league_name": "English Women's Championship",
        "label": [
            "2019/2020",
            "2018/2019"
        ]
    },
    "LD_SP": {
        "league_name": "Scottish Premiership",
        "label": [
            "2019/2020",
            "2018/2019"
        ]
    },
    "LD_S2": {
        "league_name": "Scottish League One",
        "label": [
            "2019/2020",
            "2018/2019"
        ]
    },
    "LD_P1": {
        "league_name": "Scottish Championship Play-offs",
        "label": [
            "2018/2019"
        ]
    },
    "LD_P2": {
        "league_name": "Scottish League One Play-offs",
        "label": [
            "2018/2019"
        ]
    },
    "LD_P3": {
        "league_name": "Scottish League Two Play-offs",
        "label": [
            "2018/2019"
        ]
    },
    "LD_PP": {
        "league_name": "Scottish Premiership Play-offs",
        "label": [
            "2018/2019"
        ]
    },
    "IG_OF": {
        "league_name": "Other Club Friendlies",
        "label": [
            "2019/2020"
        ]
    },
    "WO_FA": {
        "league_name": "Women's FA Cup",
        "label": [
            "2019/2020",
            "2018/2019",
            "2017/2018",
            "2016/2017",
            "2015/2016",
            "2014/2015",
            "2013/2014",
            "2012/2013"
        ]
    },
    "WO_WSLC": {
        "league_name": "FA Women's Continental League Cup",
        "label": [
            "2019/2020",
            "2018/2019",
            "2017/2018",
            "2016/2017"
        ]
    },
    "WO_CL": {
        "league_name": "Women's Champions League",
        "label": [
            "2019/2020"
        ]
    },
    "ES_PF": {
        "league_name": "Primera Divisi\u00f3n Femenina",
        "label": [
            "2019/2020",
            "2018/2019",
            "2017/2018"
        ]
    },
    "ES_SF": {
        "league_name": "Spanish Supercopa Femenina",
        "label": [
            "2019/2020"
        ]
    },
    "EC_SC": {
        "league_name": "Supercopa de Ecuador",
        "label": [
            "2019/2020"
        ]
    }
}